LICENSE
MANIFEST.in
README.md
pyproject.toml
setup.py
climetlab_s2s_ai_challenge/__init__.py
climetlab_s2s_ai_challenge/availability.py
climetlab_s2s_ai_challenge/benchmark.py
climetlab_s2s_ai_challenge/extra.py
climetlab_s2s_ai_challenge/fields.py
climetlab_s2s_ai_challenge/info.py
climetlab_s2s_ai_challenge/input.yaml
climetlab_s2s_ai_challenge/ncep_hindcast_only.yaml
climetlab_s2s_ai_challenge/observations.py
climetlab_s2s_ai_challenge/s2s_mergers.py
climetlab_s2s_ai_challenge/test_input.yaml
climetlab_s2s_ai_challenge/test_input_dev.yaml
climetlab_s2s_ai_challenge/training_input.yaml
climetlab_s2s_ai_challenge/training_input_dev.yaml
climetlab_s2s_ai_challenge.egg-info/PKG-INFO
climetlab_s2s_ai_challenge.egg-info/SOURCES.txt
climetlab_s2s_ai_challenge.egg-info/dependency_links.txt
climetlab_s2s_ai_challenge.egg-info/entry_points.txt
climetlab_s2s_ai_challenge.egg-info/requires.txt
climetlab_s2s_ai_challenge.egg-info/top_level.txt
climetlab_s2s_ai_challenge.egg-info/zip-safe